sysapi/__init__.py
sysapi/backend.py
sysapi/env.py
sysapi/file.py
sysapi/logs.py
sysapi/main.py
sysapi/preptest.py
sysapi/snapshot.py
sysapi/status.py
sysapi/user.py
sysapi-0.0.53.data/data/config.json
sysapi-0.0.53.data/data/params.json
sysapi-0.0.53.data/scripts/cleanup.sh
sysapi-0.0.53.data/scripts/preptest.sh
sysapi-0.0.53.dist-info/METADATA
sysapi-0.0.53.dist-info/WHEEL
sysapi-0.0.53.dist-info/top_level.txt
sysapi-0.0.53.dist-info/RECORD
