Metadata-Version: 2.1
Name: sysapi
Version: 0.0.53
Summary: A REST API service to query and manage the SAFER-STORAGE backup and storage in space in time dimensions
Home-page: https://gitlab.safer-storage.com/safer-dev-priv/nas-sysapi
Author: Olivier Dalle
Author-email: olivier@safer-storage.com
License: UNKNOWN
Platform: UNKNOWN
Classifier: Programming Language :: Python :: 3
Classifier: License :: OSI Approved :: European Union Public Licence 1.2 (EUPL 1.2)
Classifier: Operating System :: POSIX :: Linux
Requires-Python: >=3.7.3
Requires-Dist: fastapi
Requires-Dist: uvicorn
Requires-Dist: email-validator
Requires-Dist: pyzfs
Requires-Dist: pickledbod
Requires-Dist: setuptools
Requires-Dist: twine
Requires-Dist: wheel
Requires-Dist: datetime
